taylorexpansion/__init__.py
taylorexpansion/series.py
tests/__init__.py
tests/test_series.py
taylorexpansion-0.1.0.dist-info/LICENSE
taylorexpansion-0.1.0.dist-info/METADATA
taylorexpansion-0.1.0.dist-info/WHEEL
taylorexpansion-0.1.0.dist-info/top_level.txt
taylorexpansion-0.1.0.dist-info/RECORD
