Metadata-Version: 2.1
Name: taylorexpansion
Version: 0.1.0
Summary: A package to compute the Taylor series expansion of a given function.
Home-page: https://github.com/vikkivarma16/taylorexpansion
Author: vikkivarma16
Author-email: vikkivarma16@gmail.com
Classifier: Programming Language :: Python :: 3
Classifier: License :: OSI Approved :: MIT License
Classifier: Operating System :: OS Independent
Requires-Python: >=3.6
License-File: LICENSE
Requires-Dist: sympy
